tea/__init__.py
tea/ignore-websocket_client.py
tea/ignore-websocket_server.py
tea/main.py
tea/request.py
tea/response.py
tea_web-0.6.0.dist-info/LICENSE
tea_web-0.6.0.dist-info/METADATA
tea_web-0.6.0.dist-info/WHEEL
tea_web-0.6.0.dist-info/top_level.txt
tea_web-0.6.0.dist-info/RECORD
