Metadata-Version: 2.1
Name: tea-web
Version: 0.6.0
Summary: Micro HTTP library with WebSocket support for Python.
Home-page: UNKNOWN
Author: orhanemree (Orhan Emre Dikicigil)
Author-email: orhanemre.dev@gmail.com
License: MIT
Platform: UNKNOWN
